openapi_mcp/__init__.py
openapi_mcp/config.py
openapi_mcp/server.py
openapi_mcp/models/__init__.py
openapi_mcp/models/endpoint.py
openapi_mcp/models/openapi.py
openapi_mcp/parsers/__init__.py
openapi_mcp/parsers/base.py
openapi_mcp/parsers/openapi_parser.py
openapi_mcp/tools/__init__.py
openapi_mcp/tools/get_endpoint_details.py
openapi_mcp/tools/list_endpoints.py
openapi_mcp/utils/__init__.py
openapi_mcp/utils/formatters.py
openapi_mcp/utils/validators.py
yonglelaoren_openapi_mcp-0.1.4.dist-info/METADATA
yonglelaoren_openapi_mcp-0.1.4.dist-info/WHEEL
yonglelaoren_openapi_mcp-0.1.4.dist-info/entry_points.txt
yonglelaoren_openapi_mcp-0.1.4.dist-info/top_level.txt
yonglelaoren_openapi_mcp-0.1.4.dist-info/RECORD
