Metadata-Version: 2.4
Name: yonglelaoren-openapi-mcp
Version: 0.1.4
Summary: OpenAPI MCP Server - 基于 Model Context Protocol 的 OpenAPI 规范解析服务器
Author-email: yongle <yonglelaoren@163.com>
Requires-Python: >=3.11
Requires-Dist: mcp[cli]>=1.25.0
Requires-Dist: prance>=23.6.0
Requires-Dist: httpx>=0.27.0
Requires-Dist: pydantic>=2.0.0
Requires-Dist: pyyaml>=6.0
Requires-Dist: openapi-spec-validator>=0.7.2
Provides-Extra: dev
Requires-Dist: pytest>=7.0.0; extra == "dev"
Requires-Dist: pytest-cov>=4.0.0; extra == "dev"
Requires-Dist: pytest-asyncio>=0.21.0; extra == "dev"
Requires-Dist: ruff>=0.1.0; extra == "dev"
Requires-Dist: mypy>=1.0.0; extra == "dev"
